Source-db/full_adder.v
module full_adder(
    input a, b, cin,
    output sum, cout
);
    assign sum  = a ^ b ^ cin;                // Sum = XOR of all inputs
    assign cout = (a & b) | (b & cin) | (a & cin); // Carry = majority function
endmodule

Source-db/tb_full_adder.v
`timescale 1ns/1ps
module tb_full_adder;
    reg a, b, cin;
    wire sum, cout;

    // Instantiate the full adder
    full_adder uut (
        .a(a),
        .b(b),
        .cin(cin),
        .sum(sum),
        .cout(cout)
    );

    initial begin
        // Dump waves
        $dumpfile("full_adder.vcd");
        $dumpvars(0, tb_full_adder);

        // Truth table
        $display(" A B Cin | Sum Cout ");
        $display("-------------------");

        a=0; b=0; cin=0; #10;
        $display(" %b %b  %b  |  %b    %b", a,b,cin,sum,cout);

        a=0; b=0; cin=1; #10;
        $display(" %b %b  %b  |  %b    %b", a,b,cin,sum,cout);

        a=0; b=1; cin=0; #10;
        $display(" %b %b  %b  |  %b    %b", a,b,cin,sum,cout);

        a=0; b=1; cin=1; #10;
        $display(" %b %b  %b  |  %b    %b", a,b,cin,sum,cout);

        a=1; b=0; cin=0; #10;
        $display(" %b %b  %b  |  %b    %b", a,b,cin,sum,cout);

        a=1; b=0; cin=1; #10;
        $display(" %b %b  %b  |  %b    %b", a,b,cin,sum,cout);

        a=1; b=1; cin=0; #10;
        $display(" %b %b  %b  |  %b    %b", a,b,cin,sum,cout);

        a=1; b=1; cin=1; #10;
        $display(" %b %b  %b  |  %b    %b", a,b,cin,sum,cout);

        $finish;
    end
endmodule

Source-db/full_adder.vcd
$date
	Sat Sep 20 01:26:38 2025
$end
$version
	Icarus Verilog
$end
$timescale
	1ps
$end
$scope module tb_full_adder $end
$var wire 1 ! sum $end
$var wire 1 " cout $end
$var reg 1 # a $end
$var reg 1 $ b $end
$var reg 1 % cin $end
$scope module uut $end
$var wire 1 # a $end
$var wire 1 $ b $end
$var wire 1 % cin $end
$var wire 1 " cout $end
$var wire 1 ! sum $end
$upscope $end
$upscope $end
$enddefinitions $end
#0
$dumpvars
0%
0$
0#
0"
0!
$end
#10000
1!
1%
#20000
0%
1$
#30000
1"
0!
1%
#40000
0"
1!
0%
0$
1#
#50000
1"
0!
1%
#60000
0%
1$
#70000
1!
1%
